gitutor/.gitutor_config
gitutor/__init__.py
gitutor/branch/__init__.py
gitutor/branch/change.py
gitutor/branch/commands.py
gitutor/branch/create.py
gitutor/branch/delete.py
gitutor/branch/utils.py
gitutor/cli.py
gitutor/compare/__init__.py
gitutor/compare/color_diff.py
gitutor/compare/commands.py
gitutor/goBack/__init__.py
gitutor/goBack/commands.py
gitutor/goBack/test_commands.py
gitutor/ignore/__init__.py
gitutor/ignore/commands.py
gitutor/ignore/tests.py
gitutor/init/__init__.py
gitutor/init/commands.py
gitutor/init/test_commands.py
gitutor/lesson/__init__.py
gitutor/lesson/commands.py
gitutor/lesson/lessons.py
gitutor/save/__init__.py
gitutor/save/commands.py
gitutor/save/test_commands.py
gitutor/util.py
gitutor-0.6.5.dist-info/entry_points.txt
gitutor-0.6.5.dist-info/WHEEL
gitutor-0.6.5.dist-info/METADATA
gitutor-0.6.5.dist-info/RECORD
